rag_orchestrator/__init__.py
rag_orchestrator/__main__.py
rag_orchestrator/agents/__init__.py
rag_orchestrator/agents/base.py
rag_orchestrator/agents/registry.py
rag_orchestrator/agents/builtin/__init__.py
rag_orchestrator/agents/builtin/compressor.py
rag_orchestrator/agents/builtin/coordinator.py
rag_orchestrator/agents/builtin/dialogue.py
rag_orchestrator/agents/builtin/drafting.py
rag_orchestrator/agents/builtin/reranker.py
rag_orchestrator/agents/builtin/retriever.py
rag_orchestrator/agents/builtin/validator.py
rag_orchestrator/api/__init__.py
rag_orchestrator/api/_state.py
rag_orchestrator/api/_state_systems.py
rag_orchestrator/api/app.py
rag_orchestrator/api/config_bridge.py
rag_orchestrator/api/imports.py
rag_orchestrator/api/routes.py
rag_orchestrator/api/routes_agents.py
rag_orchestrator/api/routes_catalog.py
rag_orchestrator/api/routes_query.py
rag_orchestrator/api/routes_telemetry.py
rag_orchestrator/batching/__init__.py
rag_orchestrator/batching/gatekeeper.py
rag_orchestrator/batching/microbatch.py
rag_orchestrator/cli/__init__.py
rag_orchestrator/cli/__main__.py
rag_orchestrator/cli/main.py
rag_orchestrator/core/__init__.py
rag_orchestrator/core/protocols.py
rag_orchestrator/core/types.py
rag_orchestrator/providers/__init__.py
rag_orchestrator/providers/rag_llm_api_provider.py
rag_orchestrator/runtime/__init__.py
rag_orchestrator/runtime/batcher_pool.py
rag_orchestrator/runtime/manager.py
rag_orchestrator/web/index.html
krionis_orchestrator-0.3.5.dist-info/METADATA
krionis_orchestrator-0.3.5.dist-info/WHEEL
krionis_orchestrator-0.3.5.dist-info/entry_points.txt
krionis_orchestrator-0.3.5.dist-info/top_level.txt
krionis_orchestrator-0.3.5.dist-info/RECORD
