Metadata-Version: 2.4
Name: krionis-orchestrator
Version: 0.3.5
Summary: Krionis Orchestrator — agentic batching and coordination on top of the Krionis Pipeline
Home-page: https://github.com/pkbythebay29/ot-rag-llm-api
Author: pkbythebay29
Author-email: kannan@haztechrisk.org
Project-URL: Homepage, https://pypi.org/project/krionis-orchestrator/
Project-URL: Source, https://github.com/pkbythebay29/ot-rag-llm-api
Classifier: Development Status :: 4 - Beta
Classifier: Programming Language :: Python :: 3
Classifier: Programming Language :: Python :: 3 :: Only
Classifier: License :: OSI Approved :: MIT License
Classifier: Operating System :: OS Independent
Classifier: Topic :: Software Development :: Libraries
Classifier: Topic :: Scientific/Engineering :: Artificial Intelligence
Requires-Python: >=3.8
Dynamic: author
Dynamic: author-email
Dynamic: classifier
Dynamic: description
Dynamic: description-content-type
Dynamic: home-page
Dynamic: project-url
Dynamic: requires-python
Dynamic: summary
